pyfeatures/__init__.py
pyfeatures/feature.py
pyfeatures/manager.py
pyfeatures/storage/__init__.py
pyfeatures/storage/base.py
pyfeatures/storage/memory.py
pyfeatures-0.1.1.dist-info/DESCRIPTION.rst
pyfeatures-0.1.1.dist-info/METADATA
pyfeatures-0.1.1.dist-info/RECORD
pyfeatures-0.1.1.dist-info/WHEEL
pyfeatures-0.1.1.dist-info/metadata.json
pyfeatures-0.1.1.dist-info/top_level.txt
